linux_parsers/__init__.py
linux_parsers/command_detection.py
linux_parsers/parsers_registry.py
linux_parsers/parsers/__init__.py
linux_parsers/parsers/exceptions.py
linux_parsers/parsers/filesystem/__init__.py
linux_parsers/parsers/filesystem/df.py
linux_parsers/parsers/filesystem/dpkg.py
linux_parsers/parsers/filesystem/du.py
linux_parsers/parsers/filesystem/etc_fstab.py
linux_parsers/parsers/filesystem/fdisk.py
linux_parsers/parsers/filesystem/ls.py
linux_parsers/parsers/filesystem/mount.py
linux_parsers/parsers/filesystem/stat.py
linux_parsers/parsers/logs/__init__.py
linux_parsers/parsers/logs/var_log_auth.py
linux_parsers/parsers/logs/var_log_cron.py
linux_parsers/parsers/logs/var_log_dpkg.py
linux_parsers/parsers/logs/var_log_maillog.py
linux_parsers/parsers/logs/var_log_messages.py
linux_parsers/parsers/logs/var_log_secure.py
linux_parsers/parsers/logs/var_log_syslog.py
linux_parsers/parsers/logs/var_log_udev.py
linux_parsers/parsers/logs/var_log_wtmp_btmp_utmp.py
linux_parsers/parsers/network/__init__.py
linux_parsers/parsers/network/arp.py
linux_parsers/parsers/network/etc_resolve_conf.py
linux_parsers/parsers/network/ip.py
linux_parsers/parsers/network/iptables.py
linux_parsers/parsers/network/netstat.py
linux_parsers/parsers/network/ping.py
linux_parsers/parsers/network/ss.py
linux_parsers/parsers/network/ufw.py
linux_parsers/parsers/process/__init__.py
linux_parsers/parsers/process/cgroups.py
linux_parsers/parsers/process/jobs.py
linux_parsers/parsers/process/lsipc.py
linux_parsers/parsers/process/proc_modules.py
linux_parsers/parsers/process/ps.py
linux_parsers/parsers/process/top.py
linux_parsers/parsers/session/__init__.py
linux_parsers/parsers/session/ac.py
linux_parsers/parsers/session/last.py
linux_parsers/parsers/session/w.py
linux_parsers/parsers/session/who.py
linux_parsers/parsers/system/__init__.py
linux_parsers/parsers/system/etc_os_release.py
linux_parsers/parsers/system/etc_systemd_file_conf.py
linux_parsers/parsers/system/free.py
linux_parsers-0.2.6.dist-info/LICENSE
linux_parsers-0.2.6.dist-info/METADATA
linux_parsers-0.2.6.dist-info/WHEEL
linux_parsers-0.2.6.dist-info/top_level.txt
linux_parsers-0.2.6.dist-info/RECORD
