Metadata-Version: 2.1
Name: linux-parsers
Version: 0.2.6
Summary: Simplest library for parsing linux commands and files
Author-email: Yechiel Babani <yechielb2000@gmail.com>
License: LICENSE
Project-URL: Repository, https://github.com/yechielb2000/linux-parsers.git
Project-URL: Issues, https://github.com/yechielb2000/linux-parsers/issues
Project-URL: Changelog, https://github.com/yechielb2000/linux-parsers/blob/main/CHANGELOG.md
Keywords: linux,parser,command,file
Classifier: Programming Language :: Python :: 3 :: Only
Requires-Python: >=3.8
License-File: LICENSE
Requires-Dist: setuptools >=75.3.2
